wqxweblib/WQXWeb.py
wqxweblib/__init__.py
wqxweblib/__main__.py
wqxweblib/common.py
wqxweblib-2.2.0.1.1.dist-info/LICENSE
wqxweblib-2.2.0.1.1.dist-info/METADATA
wqxweblib-2.2.0.1.1.dist-info/WHEEL
wqxweblib-2.2.0.1.1.dist-info/top_level.txt
wqxweblib-2.2.0.1.1.dist-info/RECORD
