Metadata-Version: 2.1
Name: wqxweblib
Version: 2.2.0.1.1
Summary: A package for interacting with the EPA's WQX Web service
Home-page: https://github.com/FlippingBinary/wqxweblib-python
Author: Jon Musselwhite
Author-email: JMusselwhite@wvstateu.edu
License: UNKNOWN
Platform: UNKNOWN
Classifier: Development Status :: 4 - Beta
Classifier: Intended Audience :: Developers
Classifier: Intended Audience :: Science/Research
Classifier: Programming Language :: Python :: 3
Classifier: License :: OSI Approved :: MIT License
Classifier: Natural Language :: English
Classifier: Operating System :: OS Independent
Classifier: Topic :: Scientific/Engineering
Classifier: Topic :: Scientific/Engineering :: Hydrology
Classifier: Topic :: Software Development :: Libraries
Classifier: Topic :: Software Development :: Libraries :: Python Modules
Requires-Python: >=3.7
License-File: LICENSE
Requires-Dist: requests (>=2.25.0)
Requires-Dist: yattag (>=1.14.0)
Requires-Dist: rfc3986 (>=1.4.0)
